process_vit_res/process_vit_res.py
process_vit_res/__init__.py
process_read/__init__.py
process_read/process_read.py
profile_HMM/__init__.py
profile_HMM/profile_HMM.py
profile_HMM/data/est_072022_emissions.pkl
profile_HMM/data/est_072022_transitions.pkl
HMMSTR-1.0.5.data/scripts/test_hmm_cython.py
c_files/hmm.pyx
c_files/viterbi.c
c_files/sequence.c
c_files/hmmutils.c
c_files/testvit.c
c_files/hmm.c
c_files/hmm.cpython-38-x86_64-linux-gnu.so
c_files/hmm.pxd
c_files/__init__.pyx
c_files/nrutil.h
c_files/hmmrand.c
c_files/test_hmm_cython.py
c_files/__init__.pxd
c_files/nrutil.c
c_files/hmm.h
KDE_stats/KDE_stats.py
KDE_stats/__init__.py
HMMSTR/HMMSTR.py
HMMSTR/__init__.py
HMMSTR/HMMSTR_v1.py
HMMSTR-1.0.5.dist-info/entry_points.txt
HMMSTR-1.0.5.dist-info/WHEEL
HMMSTR-1.0.5.dist-info/top_level.txt
HMMSTR-1.0.5.dist-info/LICENSE
HMMSTR-1.0.5.dist-info/RECORD
HMMSTR-1.0.5.dist-info/METADATA
HMMSTR_utils/__init__.py
HMMSTR_utils/HMMSTR_utils.py
HMMSTR_utils/HMMSTR_utils_v1.py
GMM_stats/__init__.py
GMM_stats/GMM_stats.py
GMM_stats/GMM_stats_v1.py
